openpolicedata/__init__.py
openpolicedata/_converters.py
openpolicedata/_preproc_utils.py
openpolicedata/_version.py
openpolicedata/_version.txt
openpolicedata/data.py
openpolicedata/dataset_id.py
openpolicedata/datasets.py
openpolicedata/datetime_parser.py
openpolicedata/defs.py
openpolicedata/exceptions.py
openpolicedata/log.py
openpolicedata/preproc.py
openpolicedata/utils.py
openpolicedata/data_loaders/__init__.py
openpolicedata/data_loaders/arcgis_class.py
openpolicedata/data_loaders/carto.py
openpolicedata/data_loaders/ckan.py
openpolicedata/data_loaders/combine_dataset.py
openpolicedata/data_loaders/csv_class.py
openpolicedata/data_loaders/data_loader.py
openpolicedata/data_loaders/excel.py
openpolicedata/data_loaders/html.py
openpolicedata/data_loaders/opendatasoft.py
openpolicedata/data_loaders/socrata.py
openpolicedata/deprecated/__init__.py
openpolicedata/deprecated/_decorators.py
openpolicedata/deprecated/_pandas.py
openpolicedata/deprecated/datasetsCompat.py
openpolicedata/deprecated/messages.py
openpolicedata/deprecated/source_table_compat.py
openpolicedata/httpio/__init__.py
openpolicedata-0.12.dist-info/licenses/LICENSE
openpolicedata-0.12.dist-info/METADATA
openpolicedata-0.12.dist-info/WHEEL
openpolicedata-0.12.dist-info/top_level.txt
openpolicedata-0.12.dist-info/RECORD
