Metadata-Version: 2.4
Name: openpolicedata
Version: 0.12
Summary: The OpenPoliceData (OPD) Python library is the most comprehensive centralized public access point for incident-level police data 
Author-email: Matt Sowd <openpolicedata@gmail.com>, Paul Otto <potto@ieee.org>
License: BSD 3-Clause License
Project-URL: homepage, https://openpolicedata.readthedocs.io/
Project-URL: documentation, https://openpolicedata.readthedocs.io/en/stable/documentation.html
Project-URL: repository, https://github.com/openpolicedata/openpolicedata
Project-URL: tracker, https://github.com/openpolicedata/openpolicedata/issues
Keywords: police data,use of force,traffic,stops,complaints,officer-involved,shootings,pandas,arcgis,socrata,police transparency,police accountability
Classifier: Intended Audience :: Science/Research
Classifier: License :: OSI Approved :: BSD License
Classifier: Operating System :: OS Independent
Classifier: Programming Language :: Python :: 3
Classifier: Programming Language :: Python :: 3.9
Classifier: Programming Language :: Python :: 3.10
Classifier: Programming Language :: Python :: 3.11
Classifier: Programming Language :: Python :: 3.12
Requires-Python: >=3.9
License-File: LICENSE
Requires-Dist: openpyxl
Requires-Dist: numpy
Requires-Dist: packaging
Requires-Dist: pandas[feather,html,parquet]<3.0.0,>=2.1.0
Requires-Dist: rapidfuzz
Requires-Dist: requests
Requires-Dist: sodapy
Requires-Dist: tqdm
Requires-Dist: typing-extensions
Requires-Dist: xlrd
Provides-Extra: optional
Requires-Dist: msoffcrypto-tool; extra == "optional"
Provides-Extra: geopandas
Requires-Dist: geopandas>=0.8; extra == "geopandas"
Provides-Extra: test
Requires-Dist: pytest; extra == "test"
Dynamic: license-file
